wgstarman/__init__.py
wgstarman/decorators.py
wgstarman/wg_conf.py
wgstarman/cli/__init__.py
wgstarman/cli/common.py
wgstarman/cli/peer.py
wgstarman/cli/protocol.py
wgstarman/cli/resolv.py
wgstarman/cli/server.py
wgstarman/cli/wgstarman.py
wgstarman/cli/wgstarman_conf.py
wgstarman/cli/wgstarman_resolvers.py
wgstarman/cli/protocol/__init__.py
wgstarman/cli/protocol/messages.py
wgstarman/cli/protocol/utils.py
wgstarman/cli/server/__init__.py
wgstarman/cli/server/command.py
wgstarman/cli/server/resolver.py
wgstarman/wgcli/__init__.py
wgstarman/wgcli/exec.py
wgstarman-0.1.10.dist-info/LICENSE
wgstarman-0.1.10.dist-info/METADATA
wgstarman-0.1.10.dist-info/WHEEL
wgstarman-0.1.10.dist-info/entry_points.txt
wgstarman-0.1.10.dist-info/top_level.txt
wgstarman-0.1.10.dist-info/RECORD
