Metadata-Version: 2.1
Name: wgstarman
Version: 0.1.10
Summary: WireGuard manager to connect two or more peers in a star VPN
Home-page: https://github.com/elegos/wgstarman
Author: Giacomo Furlan
Author-email: opensource@giacomofurlan.name
License: MIT
Keywords: vpn,wireguard,cli,star,unix,posix,linux
Platform: UNKNOWN
Classifier: Development Status :: 4 - Beta
Classifier: License :: OSI Approved :: MIT License
Classifier: Natural Language :: English
Classifier: Operating System :: POSIX :: Linux
Classifier: Programming Language :: Python :: 3
Classifier: Topic :: System :: Networking
Classifier: Topic :: Utilities
Requires-Python: >=3.8
License-File: LICENSE
Requires-Dist: cryptography
